chi2comb/_testit.py
chi2comb/_chi2comb.py
chi2comb/interface.h
chi2comb/__init__.py
chi2comb/_ffi.abi3.so
chi2comb/test/test_chi2comb.py
chi2comb/test/__init__.py
chi2comb-0.1.0.dist-info/LICENSE.md
chi2comb-0.1.0.dist-info/top_level.txt
chi2comb-0.1.0.dist-info/RECORD
chi2comb-0.1.0.dist-info/METADATA
chi2comb-0.1.0.dist-info/WHEEL
chi2comb.libs/libchi2comb-58d34faa.so.0.0.3
