Metadata-Version: 2.1
Name: chi2comb
Version: 0.1.0
Summary: Linear combination of independent noncentral chi-squared random variables
Home-page: https://github.com/limix/chi2comb-py
Author: Danilo Horta
Author-email: horta@ebi.ac.uk
Maintainer: Danilo Horta
Maintainer-email: horta@ebi.ac.uk
License: MIT
Download-URL: https://github.com/limix/chi2comb-py
Keywords: chi-squared,probability,distribution
Platform: Windows
Platform: MacOS
Platform: Linux
Classifier: Development Status :: 5 - Production/Stable
Classifier: Environment :: Console
Classifier: License :: OSI Approved :: MIT License
Classifier: Operating System :: OS Independent
Classifier: Programming Language :: Python
Requires-Dist: cffi (>=1.11.5)
Requires-Dist: pytest (>=5)
Requires-Dist: pytest-doctestplus (>=0.8.0)
